mcpcat_api/__init__.py
mcpcat_api/api_client.py
mcpcat_api/api_response.py
mcpcat_api/configuration.py
mcpcat_api/exceptions.py
mcpcat_api/rest.py
mcpcat_api/api/__init__.py
mcpcat_api/api/events_api.py
mcpcat_api/api/schema_api.py
mcpcat_api/models/__init__.py
mcpcat_api/models/event_accepted_response.py
mcpcat_api/models/publish_event_request.py
mcpcat_api/test/__init__.py
mcpcat_api/test/test_event_accepted_response.py
mcpcat_api/test/test_events_api.py
mcpcat_api/test/test_publish_event_request.py
mcpcat_api/test/test_schema_api.py
mcpcat_api-0.1.3.dist-info/METADATA
mcpcat_api-0.1.3.dist-info/WHEEL
mcpcat_api-0.1.3.dist-info/top_level.txt
mcpcat_api-0.1.3.dist-info/RECORD
