Metadata-Version: 2.4
Name: mcpcat_api
Version: 0.1.3
Requires-Dist: urllib3>=1.25.3
Requires-Dist: python-dateutil
Requires-Dist: pydantic<3,>=2.0.0
Dynamic: requires-dist
